gridmaster/__init__.py
gridmaster/gridmaster_class.py
gridmaster/model_search.py
gridmaster/plot_utils.py
gridmaster-0.5.4.dist-info/LICENSE
gridmaster-0.5.4.dist-info/METADATA
gridmaster-0.5.4.dist-info/WHEEL
gridmaster-0.5.4.dist-info/top_level.txt
gridmaster-0.5.4.dist-info/RECORD
