Metadata-Version: 2.1
Name: gridmaster
Version: 0.5.4
Summary: A lightweight multi-stage grid search AutoML framework for classifiers. GridMaster v0.2.0: Log-scale search + plot customization features
Home-page: https://github.com/wins-wang/GridMaster.git
Author: Winston Wang
Author-email: mail@winston-wang.com
License: MIT
Project-URL: Documentation, https://gridmaster.readthedocs.io
Project-URL: Source, https://github.com/wins-wang/GridMaster
Project-URL: Bug Tracker, https://github.com/wins-wang/GridMaster/issues
Platform: UNKNOWN
Classifier: Programming Language :: Python :: 3
Classifier: License :: OSI Approved :: MIT License
Classifier: Operating System :: OS Independent
Classifier: Intended Audience :: Science/Research
Classifier: Topic :: Scientific/Engineering :: Artificial Intelligence
Requires-Python: >=3.7
License-File: LICENSE
Requires-Dist: scikit-learn (>=1.0)
Requires-Dist: xgboost (>=1.5)
Requires-Dist: lightgbm (>=3.3)
Requires-Dist: catboost (>=1.0)
Requires-Dist: pandas (>=1.1)
Requires-Dist: numpy (>=1.19)
Requires-Dist: matplotlib (>=3.3)
Requires-Dist: joblib (>=1.0)
